trustplutusmr/__init__.py
trustplutusmr/config/__init__.py
trustplutusmr/config/aesgcm_cipher_text.bin
trustplutusmr/config/aesgcm_key.bin
trustplutusmr/config/aesgcm_nonce.bin
trustplutusmr/config/aesgcm_tag.bin
trustplutusmr/config/constants.py
trustplutusmr/config/var.json
trustplutusmr/dist/trustplustus_mr-0.1.0.tar.gz
trustplutusmr/dist/trustplutus_mr-0.1.0.tar.gz
trustplutusmr/logs/mylog.txt
trustplutusmr/main.py
trustplutusmr/utils/__init__.py
trustplutusmr/utils/helpers.py
trustplutusmr/utils/logs.py
trustplutusmr/utils/secretStore.py
trustplutusmr/utils/webscraping.py
trustplutusmr-1.6.dist-info/LICENSE
trustplutusmr-1.6.dist-info/METADATA
trustplutusmr-1.6.dist-info/WHEEL
trustplutusmr-1.6.dist-info/RECORD
