Metadata-Version: 2.1
Name: trustplutusmr
Version: 1.6
Summary: Entity Market Research
License: OSI Approved :: GNU General Public License v3 (GPLv3)
Author: Rolf Lobo
Requires-Python: ==3.10.13
Classifier: License :: Other/Proprietary License
Classifier: Programming Language :: Python :: 3
Requires-Dist: beautifulsoup4 (>=4.9.3,<5.0.0)
Requires-Dist: chardet (>=5.2.0,<6.0.0)
Requires-Dist: courlan (>=1.0.0,<2.0.0)
Requires-Dist: gnews (>=0.3.6,<0.4.0)
Requires-Dist: huggingface-hub (>=0.21.4,<0.22.0)
Requires-Dist: justext (>=3.0.0,<4.0.0)
Requires-Dist: langdetect (>=1.0.9,<2.0.0)
Requires-Dist: loga (>=1.0.0,<2.0.0)
Requires-Dist: lxml (>=5.1.0,<6.0.0)
Requires-Dist: newspaper3k (>=0.2.8,<0.3.0)
Requires-Dist: nlpretext (>=1.2.2,<2.0.0)
Requires-Dist: python-iso639 (>=2024.2.7,<2025.0.0)
Requires-Dist: requests (>=2.26.0,<3.0.0)
Requires-Dist: safetensors (>=0.4.2,<0.5.0)
Requires-Dist: tokenizers (>=0.15.2,<0.16.0)
Requires-Dist: torch (>=2.2.1,<3.0.0)
Requires-Dist: torchaudio (>=2.2.1,<3.0.0)
Requires-Dist: torchvision (>=0.17.1,<0.18.0)
Requires-Dist: transformers (>=4.38.2,<5.0.0)
Requires-Dist: urllib3 (>=1.26.18,<2.0.0)
Requires-Dist: xhtml2pdf (>=0.2.15,<0.3.0)
